object_ql/__init__.py
object_ql/_version.py
object_ql/oql.py
object_ql-0.1.2.dist-info/LICENSE
object_ql-0.1.2.dist-info/METADATA
object_ql-0.1.2.dist-info/WHEEL
object_ql-0.1.2.dist-info/top_level.txt
object_ql-0.1.2.dist-info/RECORD
