Metadata-Version: 2.1
Name: object-ql
Version: 0.1.2
Summary: Object query language for dictionary-like data
Home-page: https://github.com/dsblank/object-ql
Author: Doug Blank
License: MIT License
Platform: Linux
Platform: Mac OS X
Platform: Windows
Classifier: License :: OSI Approved :: MIT License
Classifier: Programming Language :: Python
Classifier: Programming Language :: Python :: 3
Classifier: Programming Language :: Python :: 3.8
Classifier: Programming Language :: Python :: 3.9
Classifier: Programming Language :: Python :: 3.10
Requires-Python: >=3.8
License-File: LICENSE
Requires-Dist: gramps
